semanticGP/__init__.py
semanticGP/base.py
semanticGP/breeding.py
semanticGP/history.py
semanticGP/multiobjective.py
semanticGP/operators.py
semanticGP/primitives.py
semanticGP/selection.py
semanticGP/util.py
semanticGP-0.1.0.dist-info/LICENSE
semanticGP-0.1.0.dist-info/METADATA
semanticGP-0.1.0.dist-info/WHEEL
semanticGP-0.1.0.dist-info/top_level.txt
semanticGP-0.1.0.dist-info/RECORD
